{
  "description": "Microsoft.DataFactory/factories/dataflows",
  "properties": {
    "apiVersion": {
      "enum": [
        "2018-06-01"
      ],
      "type": "string"
    },
    "name": {
      "description": "The data flow name.",
      "oneOf": [
        {
          "maxLength": 260,
          "minLength": 1,
          "pattern": "^[A-Za-z0-9_][^<>*#.%&:\\\\+?/]*$",
          "type": "string"
        },
        {
          "$ref": "https://schema.management.azure.com/schemas/common/definitions.json#/definitions/expression"
        }
      ]
    },
    "properties": {
      "description": "Data flow properties.",
      "oneOf": [
        {
          "$ref": "#/definitions/DataFlow"
        },
        {
          "$ref": "https://schema.management.azure.com/schemas/common/definitions.json#/definitions/expression"
        }
      ]
    },
    "type": {
      "enum": [
        "Microsoft.DataFactory/factories/dataflows"
      ],
      "type": "string"
    }
  },
  "required": [
    "name",
    "properties",
    "apiVersion",
    "type"
  ],
  "type": "object"
}