{
  "description": "Microsoft.AppPlatform/Spring/jobs",
  "properties": {
    "apiVersion": {
      "enum": [
        "2024-05-01-preview"
      ],
      "type": "string"
    },
    "name": {
      "description": "The name of the Job resource.",
      "oneOf": [
        {
          "pattern": "^[a-z][a-z0-9-]*[a-z0-9]$",
          "type": "string"
        },
        {
          "$ref": "https://schema.management.azure.com/schemas/common/definitions.json#/definitions/expression"
        }
      ]
    },
    "properties": {
      "description": "Properties of the Job resource",
      "oneOf": [
        {
          "$ref": "#/definitions/JobResourceProperties"
        },
        {
          "$ref": "https://schema.management.azure.com/schemas/common/definitions.json#/definitions/expression"
        }
      ]
    },
    "type": {
      "enum": [
        "Microsoft.AppPlatform/Spring/jobs"
      ],
      "type": "string"
    }
  },
  "required": [
    "name",
    "properties",
    "apiVersion",
    "type"
  ],
  "type": "object"
}