{
  "description": "Microsoft.Network/applicationGateways/privateEndpointConnections",
  "properties": {
    "apiVersion": {
      "enum": [
        "2024-07-01"
      ],
      "type": "string"
    },
    "id": {
      "description": "Resource ID.",
      "type": "string"
    },
    "name": {
      "description": "The name of the application gateway private endpoint connection.",
      "type": "string"
    },
    "properties": {
      "description": "Properties of the application gateway private endpoint connection.",
      "oneOf": [
        {
          "$ref": "#/definitions/ApplicationGatewayPrivateEndpointConnectionProperties"
        },
        {
          "$ref": "https://schema.management.azure.com/schemas/common/definitions.json#/definitions/expression"
        }
      ]
    },
    "type": {
      "enum": [
        "Microsoft.Network/applicationGateways/privateEndpointConnections"
      ],
      "type": "string"
    }
  },
  "required": [
    "name",
    "properties",
    "apiVersion",
    "type"
  ],
  "type": "object"
}