{
  "description": "Microsoft.CognitiveServices/accounts/encryptionScopes",
  "properties": {
    "apiVersion": {
      "enum": [
        "2025-06-01"
      ],
      "type": "string"
    },
    "name": {
      "description": "The name of the encryptionScope associated with the Cognitive Services Account",
      "oneOf": [
        {
          "pattern": "^[a-zA-Z0-9][a-zA-Z0-9_.-]*$",
          "type": "string"
        },
        {
          "$ref": "https://schema.management.azure.com/schemas/common/definitions.json#/definitions/expression"
        }
      ]
    },
    "properties": {
      "description": "Properties of Cognitive Services EncryptionScope.",
      "oneOf": [
        {
          "$ref": "#/definitions/EncryptionScopeProperties"
        },
        {
          "$ref": "https://schema.management.azure.com/schemas/common/definitions.json#/definitions/expression"
        }
      ]
    },
    "tags": {
      "description": "Resource tags.",
      "oneOf": [
        {
          "additionalProperties": {
            "type": "string"
          },
          "properties": {},
          "type": "object"
        },
        {
          "$ref": "https://schema.management.azure.com/schemas/common/definitions.json#/definitions/expression"
        }
      ]
    },
    "type": {
      "enum": [
        "Microsoft.CognitiveServices/accounts/encryptionScopes"
      ],
      "type": "string"
    }
  },
  "required": [
    "name",
    "properties",
    "apiVersion",
    "type"
  ],
  "type": "object"
}