{
  "description": "Microsoft.Compute/galleries/images/versions",
  "properties": {
    "apiVersion": {
      "enum": [
        "2024-03-03"
      ],
      "type": "string"
    },
    "location": {
      "description": "Resource location",
      "type": "string"
    },
    "name": {
      "description": "The name of the gallery image version to be created. Needs to follow semantic version name pattern: The allowed characters are digit and period. Digits must be within the range of a 32-bit integer. Format: <MajorVersion>.<MinorVersion>.<Patch>",
      "type": "string"
    },
    "properties": {
      "description": "Describes the properties of a gallery image version.",
      "oneOf": [
        {
          "$ref": "#/definitions/GalleryImageVersionProperties"
        },
        {
          "$ref": "https://schema.management.azure.com/schemas/common/definitions.json#/definitions/expression"
        }
      ]
    },
    "tags": {
      "description": "Resource tags",
      "oneOf": [
        {
          "additionalProperties": {
            "type": "string"
          },
          "properties": {},
          "type": "object"
        },
        {
          "$ref": "https://schema.management.azure.com/schemas/common/definitions.json#/definitions/expression"
        }
      ]
    },
    "type": {
      "enum": [
        "Microsoft.Compute/galleries/images/versions"
      ],
      "type": "string"
    }
  },
  "required": [
    "name",
    "properties",
    "apiVersion",
    "type"
  ],
  "type": "object"
}