{
  "description": "Microsoft.Compute/images",
  "properties": {
    "apiVersion": {
      "enum": [
        "2024-11-01"
      ],
      "type": "string"
    },
    "extendedLocation": {
      "description": "The extended location of the Image.",
      "oneOf": [
        {
          "$ref": "#/definitions/ExtendedLocation"
        },
        {
          "$ref": "https://schema.management.azure.com/schemas/common/definitions.json#/definitions/expression"
        }
      ]
    },
    "location": {
      "description": "Resource location",
      "type": "string"
    },
    "name": {
      "description": "The name of the image.",
      "type": "string"
    },
    "properties": {
      "description": "Describes the properties of an Image.",
      "oneOf": [
        {
          "$ref": "#/definitions/ImageProperties"
        },
        {
          "$ref": "https://schema.management.azure.com/schemas/common/definitions.json#/definitions/expression"
        }
      ]
    },
    "tags": {
      "description": "Resource tags",
      "oneOf": [
        {
          "additionalProperties": {
            "type": "string"
          },
          "properties": {},
          "type": "object"
        },
        {
          "$ref": "https://schema.management.azure.com/schemas/common/definitions.json#/definitions/expression"
        }
      ]
    },
    "type": {
      "enum": [
        "Microsoft.Compute/images"
      ],
      "type": "string"
    }
  },
  "required": [
    "name",
    "properties",
    "apiVersion",
    "type"
  ],
  "type": "object"
}