{
  "description": "Microsoft.ScVmm/vmmServers/inventoryItems",
  "properties": {
    "apiVersion": {
      "enum": [
        "2025-03-13"
      ],
      "type": "string"
    },
    "kind": {
      "description": "Metadata used by portal/tooling/etc to render different UX experiences for resources of the same type; e.g. ApiApps are a kind of Microsoft.Web/sites type.  If supported, the resource provider must validate and persist this value.",
      "type": "string"
    },
    "name": {
      "description": "Name of the inventoryItem.",
      "oneOf": [
        {
          "pattern": "^[0-9a-fA-F]{8}-[0-9a-fA-F]{4}-[0-9a-fA-F]{4}-[0-9a-fA-F]{4}-[0-9a-fA-F]{12}$",
          "type": "string"
        },
        {
          "$ref": "https://schema.management.azure.com/schemas/common/definitions.json#/definitions/expression"
        }
      ]
    },
    "properties": {
      "description": "The resource-specific properties for this resource.",
      "oneOf": [
        {
          "$ref": "#/definitions/InventoryItemProperties"
        },
        {
          "$ref": "https://schema.management.azure.com/schemas/common/definitions.json#/definitions/expression"
        }
      ]
    },
    "type": {
      "enum": [
        "Microsoft.ScVmm/vmmServers/inventoryItems"
      ],
      "type": "string"
    }
  },
  "required": [
    "name",
    "properties",
    "apiVersion",
    "type"
  ],
  "type": "object"
}