{
  "description": "Microsoft.Network/firewallPolicies/signatureOverrides",
  "properties": {
    "apiVersion": {
      "enum": [
        "2024-07-01"
      ],
      "type": "string"
    },
    "id": {
      "description": "Will contain the resource id of the signature override resource",
      "type": "string"
    },
    "name": {
      "oneOf": [
        {
          "pattern": "^.*/default$",
          "type": "string"
        },
        {
          "$ref": "https://schema.management.azure.com/schemas/common/definitions.json#/definitions/expression"
        }
      ]
    },
    "properties": {
      "description": "Will contain the properties of the resource (the actual signature overrides)",
      "oneOf": [
        {
          "$ref": "#/definitions/SignaturesOverridesProperties"
        },
        {
          "$ref": "https://schema.management.azure.com/schemas/common/definitions.json#/definitions/expression"
        }
      ]
    },
    "type": {
      "enum": [
        "Microsoft.Network/firewallPolicies/signatureOverrides"
      ],
      "type": "string"
    }
  },
  "required": [
    "name",
    "properties",
    "apiVersion",
    "type"
  ],
  "type": "object"
}